colorparse.py
colorparse-1.1.6.dist-info/LICENSE
colorparse-1.1.6.dist-info/METADATA
colorparse-1.1.6.dist-info/WHEEL
colorparse-1.1.6.dist-info/entry_points.txt
colorparse-1.1.6.dist-info/top_level.txt
colorparse-1.1.6.dist-info/RECORD
