Metadata-Version: 2.1
Name: colorparse
Version: 1.1.6
Summary: A string-coloring package for terminals
Home-page: https://github.com/tubi-carrillo/colorparse
Author: Esteban Carrillo
Author-email: esteban.ac.naranjo@gmail.com
License: UNKNOWN
Keywords: colorparse,terminal,color,ansi
Platform: UNKNOWN
Classifier: Programming Language :: Python :: 3
Classifier: License :: OSI Approved :: MIT License
Classifier: Operating System :: OS Independent
